{"republic-of-adygea":{"tags":["green","yellow"],"colors":[{"hex":"#2a6b11","percent":95,"tag":"green"},{"hex":"#ffff00","percent":3,"tag":"yellow"}]},"altai-republic":{"tags":["white","blue"],"colors":[{"hex":"#ffffff","percent":71,"tag":"white"},{"hex":"#3399ff","percent":29,"tag":"blue"}]},"republic-of-bashkortostan":{"tags":["blue","green","white","yellow"],"colors":[{"hex":"#0070ff","percent":33,"tag":"blue"},{"hex":"#007000","percent":33,"tag":"green"},{"hex":"#ffffff","percent":31,"tag":"white"},{"hex":"#ffd700","percent":1,"tag":"yellow"}]},"republic-of-buryatia":{"tags":["blue","yellow","white"],"colors":[{"hex":"#0039a6","percent":47,"tag":"blue"},{"hex":"#ffd900","percent":27,"tag":"yellow"},{"hex":"#ffffff","percent":25,"tag":"white"}]},"chechen-republic":{"tags":["green","red","white","yellow"],"colors":[{"hex":"#2b7338","percent":53,"tag":"green"},{"hex":"#da251d","percent":29,"tag":"red"},{"hex":"#ffffff","percent":15,"tag":"white"},{"hex":"#ffcc00","percent":1,"tag":"yellow"}]},"chuvash-republic":{"tags":["yellow","red"],"colors":[{"hex":"#fce304","percent":68,"tag":"yellow"},{"hex":"#a42404","percent":28,"tag":"red"}]},"republic-of-crimea":{"tags":["white","cyan","red"],"colors":[{"hex":"#ffffff","percent":67,"tag":"white"},{"hex":"#006fb0","percent":17,"tag":"cyan"},{"hex":"#da251d","percent":17,"tag":"red"}]},"republic-of-dagestan":{"tags":["green","blue","red"],"colors":[{"hex":"#00923f","percent":33,"tag":"green"},{"hex":"#0039a6","percent":33,"tag":"blue"},{"hex":"#d81e05","percent":33,"tag":"red"}]},"republic-of-ingushetia":{"tags":["white","green","red"],"colors":[{"hex":"#ffffff","percent":60,"tag":"white"},{"hex":"#00923f","percent":33,"tag":"green"},{"hex":"#d81e05","percent":6,"tag":"red"}]},"kabardino-balkar-republic":{"tags":["green","blue","white"],"colors":[{"hex":"#00923f","percent":36,"tag":"green"},{"hex":"#3399ff","percent":35,"tag":"blue"},{"hex":"#ffffff","percent":29,"tag":"white"}]},"republic-of-kalmykia":{"tags":["yellow","cyan","white"],"colors":[{"hex":"#ffd000","percent":82,"tag":"yellow"},{"hex":"#00b0e0","percent":13,"tag":"cyan"},{"hex":"#ffffff","percent":4,"tag":"white"}]},"karachay-cherkess-republic":{"tags":["cyan","red","green","yellow","white"],"colors":[{"hex":"#0090d0","percent":33,"tag":"cyan"},{"hex":"#e02010","percent":33,"tag":"red"},{"hex":"#007030","percent":31,"tag":"green"},{"hex":"#ffb000","percent":1,"tag":"yellow"},{"hex":"#ffffff","percent":1,"tag":"white"}]},"republic-of-karelia":{"tags":["red","cyan","green"],"colors":[{"hex":"#d50000","percent":33,"tag":"red"},{"hex":"#00aaff","percent":33,"tag":"cyan"},{"hex":"#008000","percent":33,"tag":"green"}]},"republic-of-khakassia":{"tags":["blue","white","red","green","yellow"],"colors":[{"hex":"#0051ba","percent":28,"tag":"blue"},{"hex":"#ffffff","percent":28,"tag":"white"},{"hex":"#d81e05","percent":28,"tag":"red"},{"hex":"#009847","percent":14,"tag":"green"},{"hex":"#ffd700","percent":2,"tag":"yellow"}]},"komi-republic":{"tags":["blue","green","white"],"colors":[{"hex":"#0039a6","percent":33,"tag":"blue"},{"hex":"#009b3a","percent":33,"tag":"green"},{"hex":"#ffffff","percent":33,"tag":"white"}]},"mari-el-republic":{"tags":["white","red","blue","yellow","black"],"colors":[{"hex":"#ffffff","percent":82,"tag":"white"},{"hex":"#a92211","percent":11,"tag":"red"},{"hex":"#405a9f","percent":2,"tag":"blue"},{"hex":"#d1a345","percent":1,"tag":"yellow"},{"hex":"#000000","percent":1,"tag":"black"}]},"republic-of-mordovia":{"tags":["white","red","blue"],"colors":[{"hex":"#ffffff","percent":46,"tag":"white"},{"hex":"#d20000","percent":29,"tag":"red"},{"hex":"#0000ff","percent":25,"tag":"blue"}]},"republic-of-north-ossetia-alania":{"tags":["white","red","yellow"],"colors":[{"hex":"#ffffff","percent":33,"tag":"white"},{"hex":"#ed1c24","percent":33,"tag":"red"},{"hex":"#ffff00","percent":33,"tag":"yellow"}]},"sakha-republic":{"tags":["cyan","green","white","red"],"colors":[{"hex":"#1199ff","percent":69,"tag":"cyan"},{"hex":"#009900","percent":13,"tag":"green"},{"hex":"#ffffff","percent":12,"tag":"white"},{"hex":"#ff2400","percent":6,"tag":"red"}]},"republic-of-tatarstan":{"tags":["green","red","white"],"colors":[{"hex":"#008000","percent":47,"tag":"green"},{"hex":"#ff0000","percent":47,"tag":"red"},{"hex":"#ffffff","percent":7,"tag":"white"}]},"tuva-republic":{"tags":["cyan","yellow","white"],"colors":[{"hex":"#63b1e5","percent":67,"tag":"cyan"},{"hex":"#fecb00","percent":17,"tag":"yellow"},{"hex":"#ffffff","percent":16,"tag":"white"}]},"udmurt-republic":{"tags":["red","black","white"],"colors":[{"hex":"#dd2211","percent":40,"tag":"red"},{"hex":"#000000","percent":33,"tag":"black"},{"hex":"#ffffff","percent":26,"tag":"white"}]},"altai-krai":{"tags":["red","blue","cyan","yellow","white"],"colors":[{"hex":"#cc0000","percent":70,"tag":"red"},{"hex":"#0080ff","percent":13,"tag":"blue"},{"hex":"#007cc3","percent":3,"tag":"cyan"},{"hex":"#f8d407","percent":3,"tag":"yellow"},{"hex":"#de411a","percent":2,"tag":"red"},{"hex":"#5b4431","percent":1,"tag":"red"},{"hex":"#fbdd73","percent":1,"tag":"yellow"},{"hex":"#1f1a17","percent":1,"tag":"red"},{"hex":"#ffffff","percent":1,"tag":"white"}]},"kamchatka-krai":{"tags":["white","blue","red","black"],"colors":[{"hex":"#ffffff","percent":63,"tag":"white"},{"hex":"#0051ba","percent":34,"tag":"blue"},{"hex":"#d81e05","percent":2,"tag":"red"},{"hex":"#000000","percent":1,"tag":"black"}]},"khabarovsk-krai":{"tags":["white","cyan","green"],"colors":[{"hex":"#ffffff","percent":42,"tag":"white"},{"hex":"#0099ff","percent":42,"tag":"cyan"},{"hex":"#008000","percent":17,"tag":"green"}]},"krasnodar-krai":{"tags":["magenta","blue","green","yellow"],"colors":[{"hex":"#ec008c","percent":37,"tag":"magenta"},{"hex":"#2a3f9d","percent":24,"tag":"blue"},{"hex":"#26b255","percent":23,"tag":"green"},{"hex":"#fbc707","percent":5,"tag":"yellow"}]},"krasnoyarsk-krai":{"tags":["red","yellow","cyan"],"colors":[{"hex":"#f91301","percent":89,"tag":"red"},{"hex":"#ee062c","percent":2,"tag":"red"},{"hex":"#ffc33c","percent":1,"tag":"yellow"},{"hex":"#00daee","percent":1,"tag":"cyan"}]},"perm-krai":{"tags":["red","white","cyan"],"colors":[{"hex":"#da251d","percent":34,"tag":"red"},{"hex":"#ffffff","percent":33,"tag":"white"},{"hex":"#0071b4","percent":31,"tag":"cyan"}]},"primorsky-krai":{"tags":["cyan","red","white","yellow"],"colors":[{"hex":"#0093dd","percent":35,"tag":"cyan"},{"hex":"#da251d","percent":33,"tag":"red"},{"hex":"#ffffff","percent":28,"tag":"white"},{"hex":"#fff500","percent":1,"tag":"yellow"}]},"stavropol-krai":{"tags":["yellow","white"],"colors":[{"hex":"#ffcc00","percent":60,"tag":"yellow"},{"hex":"#ffffff","percent":37,"tag":"white"}]},"zabaykalsky-krai":{"tags":["green","red","yellow"],"colors":[{"hex":"#00923f","percent":37,"tag":"green"},{"hex":"#d81e05","percent":37,"tag":"red"},{"hex":"#ffd700","percent":25,"tag":"yellow"}]},"amur-oblast":{"tags":["red","blue","white"],"colors":[{"hex":"#e00000","percent":66,"tag":"red"},{"hex":"#0064c8","percent":25,"tag":"blue"},{"hex":"#ffffff","percent":8,"tag":"white"}]},"arkhangelsk-oblast":{"tags":["white","cyan","yellow"],"colors":[{"hex":"#fefefe","percent":65,"tag":"white"},{"hex":"#029ad2","percent":27,"tag":"cyan"},{"hex":"#d4b26b","percent":1,"tag":"yellow"},{"hex":"#f9f0d4","percent":1,"tag":"white"}]},"astrakhan-oblast":{"tags":["cyan","white","yellow","green"],"colors":[{"hex":"#1d82b3","percent":85,"tag":"cyan"},{"hex":"#ffffff","percent":4,"tag":"white"},{"hex":"#fff500","percent":3,"tag":"yellow"},{"hex":"#eb8a1b","percent":3,"tag":"yellow"},{"hex":"#00a13a","percent":1,"tag":"green"}]},"belgorod-oblast":{"tags":["cyan","green","black","red","white"],"colors":[{"hex":"#0064b1","percent":22,"tag":"cyan"},{"hex":"#00a54d","percent":20,"tag":"green"},{"hex":"#000000","percent":19,"tag":"black"},{"hex":"#ed1b21","percent":19,"tag":"red"},{"hex":"#ffffff","percent":13,"tag":"white"},{"hex":"#34b7eb","percent":3,"tag":"cyan"}]},"bryansk-oblast":{"tags":["red","yellow","blue","green"],"colors":[{"hex":"#a32638","percent":80,"tag":"red"},{"hex":"#f2d300","percent":5,"tag":"yellow"},{"hex":"#40187a","percent":5,"tag":"blue"},{"hex":"#9b7d23","percent":3,"tag":"yellow"},{"hex":"#d82819","percent":1,"tag":"red"},{"hex":"#008d21","percent":1,"tag":"green"}]},"chelyabinsk-oblast":{"tags":["red","yellow","white","gray"],"colors":[{"hex":"#d61a0c","percent":70,"tag":"red"},{"hex":"#fecc00","percent":17,"tag":"yellow"},{"hex":"#ffffff","percent":5,"tag":"white"},{"hex":"#c1c1c1","percent":2,"tag":"gray"}]},"irkutsk-oblast":{"tags":["cyan","white","black","green"],"colors":[{"hex":"#0099ff","percent":49,"tag":"cyan"},{"hex":"#ffffff","percent":41,"tag":"white"},{"hex":"#110a0b","percent":3,"tag":"black"},{"hex":"#359336","percent":1,"tag":"green"},{"hex":"#359435","percent":1,"tag":"green"}]},"ivanovo-oblast":{"tags":["red","cyan","white","yellow"],"colors":[{"hex":"#e21c2a","percent":37,"tag":"red"},{"hex":"#009fe0","percent":36,"tag":"cyan"},{"hex":"#ffffff","percent":11,"tag":"white"},{"hex":"#ffcc00","percent":4,"tag":"yellow"}]},"kaliningrad-oblast":{"tags":["blue","red","yellow","white"],"colors":[{"hex":"#283595","percent":42,"tag":"blue"},{"hex":"#ec1a23","percent":38,"tag":"red"},{"hex":"#fdf100","percent":15,"tag":"yellow"},{"hex":"#ffffff","percent":2,"tag":"white"}]},"kaluga-oblast":{"tags":["green","red","white","yellow"],"colors":[{"hex":"#00a652","percent":41,"tag":"green"},{"hex":"#e40102","percent":36,"tag":"red"},{"hex":"#ffffff","percent":18,"tag":"white"},{"hex":"#ffcc00","percent":2,"tag":"yellow"},{"hex":"#1f1a17","percent":1,"tag":"red"}]},"kemerovo-oblast":{"tags":["red","blue","yellow"],"colors":[{"hex":"#d81e05","percent":68,"tag":"red"},{"hex":"#0051ba","percent":27,"tag":"blue"},{"hex":"#ffd700","percent":2,"tag":"yellow"},{"hex":"#d9251d","percent":1,"tag":"red"},{"hex":"#1f1a17","percent":1,"tag":"red"}]},"kirov-oblast":{"tags":["white","cyan","green","yellow","red"],"colors":[{"hex":"#ffffff","percent":59,"tag":"white"},{"hex":"#007cc3","percent":13,"tag":"cyan"},{"hex":"#00923f","percent":12,"tag":"green"},{"hex":"#f8c300","percent":9,"tag":"yellow"},{"hex":"#da251d","percent":1,"tag":"red"}]},"kostroma-oblast":{"tags":["red","blue","yellow"],"colors":[{"hex":"#d20000","percent":50,"tag":"red"},{"hex":"#0039a6","percent":42,"tag":"blue"},{"hex":"#faeb00","percent":3,"tag":"yellow"},{"hex":"#f8c300","percent":1,"tag":"yellow"}]},"kurgan-oblast":{"tags":["white","green"],"colors":[{"hex":"#ffffff","percent":70,"tag":"white"},{"hex":"#008040","percent":30,"tag":"green"}]},"kursk-oblast":{"tags":["red","white","black","yellow","blue"],"colors":[{"hex":"#e51919","percent":57,"tag":"red"},{"hex":"#ffffff","percent":14,"tag":"white"},{"hex":"#000000","percent":12,"tag":"black"},{"hex":"#f5c501","percent":11,"tag":"yellow"},{"hex":"#354990","percent":1,"tag":"blue"}]},"leningrad-oblast":{"tags":["white","red","blue","cyan"],"colors":[{"hex":"#ffffff","percent":64,"tag":"white"},{"hex":"#d52b1e","percent":15,"tag":"red"},{"hex":"#0039a6","percent":15,"tag":"blue"},{"hex":"#149adb","percent":4,"tag":"cyan"}]},"lipetsk-oblast":{"tags":["red","green","yellow","black"],"colors":[{"hex":"#d20000","percent":60,"tag":"red"},{"hex":"#008e1f","percent":18,"tag":"green"},{"hex":"#ffd700","percent":12,"tag":"yellow"},{"hex":"#000000","percent":1,"tag":"black"}]},"magadan-oblast":{"tags":["red","blue","white","cyan"],"colors":[{"hex":"#c42730","percent":70,"tag":"red"},{"hex":"#2e418a","percent":17,"tag":"blue"},{"hex":"#ffffff","percent":6,"tag":"white"},{"hex":"#183883","percent":3,"tag":"blue"},{"hex":"#0093dd","percent":2,"tag":"cyan"}]},"moscow-oblast":{"tags":["red","white"],"colors":[{"hex":"#e21c2a","percent":97,"tag":"red"},{"hex":"#ffffff","percent":1,"tag":"white"}]},"murmansk-oblast":{"tags":["blue","red","yellow"],"colors":[{"hex":"#395c98","percent":71,"tag":"blue"},{"hex":"#d5312b","percent":20,"tag":"red"},{"hex":"#edbb32","percent":5,"tag":"yellow"}]},"nizhny-novgorod-oblast":{"tags":["white","yellow","cyan","red"],"colors":[{"hex":"#ffffff","percent":86,"tag":"white"},{"hex":"#dededd","percent":4,"tag":"white"},{"hex":"#f8c300","percent":3,"tag":"yellow"},{"hex":"#007cc3","percent":2,"tag":"cyan"},{"hex":"#70614e","percent":1,"tag":"yellow"},{"hex":"#d52e26","percent":1,"tag":"red"}]},"novgorod-oblast":{"tags":["white","red","blue","black","yellow","cyan"],"colors":[{"hex":"#ffffff","percent":39,"tag":"white"},{"hex":"#d03528","percent":26,"tag":"red"},{"hex":"#2f418c","percent":25,"tag":"blue"},{"hex":"#cccccc","percent":4,"tag":"white"},{"hex":"#000000","percent":3,"tag":"black"},{"hex":"#ddb523","percent":1,"tag":"yellow"},{"hex":"#056a9e","percent":1,"tag":"cyan"}]},"novosibirsk-oblast":{"tags":["red","green","white","blue","black","yellow"],"colors":[{"hex":"#d20000","percent":28,"tag":"red"},{"hex":"#008e1f","percent":27,"tag":"green"},{"hex":"#ffffff","percent":27,"tag":"white"},{"hex":"#0039a6","percent":10,"tag":"blue"},{"hex":"#000000","percent":6,"tag":"black"},{"hex":"#ffd700","percent":1,"tag":"yellow"}]},"omsk-oblast":{"tags":["red","white","blue"],"colors":[{"hex":"#e00000","percent":67,"tag":"red"},{"hex":"#ffffff","percent":22,"tag":"white"},{"hex":"#0000ff","percent":11,"tag":"blue"}]},"orenburg-oblast":{"tags":["red","yellow","cyan","white"],"colors":[{"hex":"#e21c2a","percent":87,"tag":"red"},{"hex":"#ffec00","percent":2,"tag":"yellow"},{"hex":"#00569f","percent":2,"tag":"cyan"},{"hex":"#ffffff","percent":1,"tag":"white"}]},"oryol-oblast":{"tags":["red","cyan","white","green"],"colors":[{"hex":"#e21c2a","percent":64,"tag":"red"},{"hex":"#008ed1","percent":26,"tag":"cyan"},{"hex":"#dedede","percent":3,"tag":"white"},{"hex":"#009240","percent":2,"tag":"green"}]},"penza-oblast":{"tags":["yellow","green","gray"],"colors":[{"hex":"#ffdc00","percent":70,"tag":"yellow"},{"hex":"#008a3e","percent":16,"tag":"green"},{"hex":"#48433e","percent":2,"tag":"gray"},{"hex":"#796c57","percent":2,"tag":"yellow"}]},"pskov-oblast":{"tags":["cyan","white","yellow","black","gray"],"colors":[{"hex":"#038cd4","percent":66,"tag":"cyan"},{"hex":"#ffffff","percent":14,"tag":"white"},{"hex":"#ffcc01","percent":10,"tag":"yellow"},{"hex":"#000000","percent":2,"tag":"black"},{"hex":"#d79500","percent":2,"tag":"yellow"},{"hex":"#adc7d6","percent":1,"tag":"gray"},{"hex":"#fed6a5","percent":1,"tag":"white"}]},"rostov-oblast":{"tags":["blue","yellow","red","white"],"colors":[{"hex":"#004e9b","percent":29,"tag":"blue"},{"hex":"#f7c500","percent":29,"tag":"yellow"},{"hex":"#b52315","percent":29,"tag":"red"},{"hex":"#ffffff","percent":13,"tag":"white"}]},"ryazan-oblast":{"tags":["yellow","red","white","green","gray"],"colors":[{"hex":"#f8c300","percent":46,"tag":"yellow"},{"hex":"#da251d","percent":26,"tag":"red"},{"hex":"#ffffff","percent":25,"tag":"white"},{"hex":"#00923f","percent":1,"tag":"green"},{"hex":"#4c4840","percent":1,"tag":"gray"}]},"sakhalin-oblast":{"tags":["cyan","white"],"colors":[{"hex":"#47a5ae","percent":96,"tag":"cyan"},{"hex":"#ffffff","percent":3,"tag":"white"}]},"samara-oblast":{"tags":["red","cyan","white","yellow","gray"],"colors":[{"hex":"#da251d","percent":30,"tag":"red"},{"hex":"#0093dd","percent":29,"tag":"cyan"},{"hex":"#ffffff","percent":22,"tag":"white"},{"hex":"#75c5f0","percent":7,"tag":"cyan"},{"hex":"#8f5444","percent":2,"tag":"red"},{"hex":"#f8c300","percent":2,"tag":"yellow"},{"hex":"#007cc3","percent":1,"tag":"cyan"},{"hex":"#605d5c","percent":1,"tag":"gray"}]},"saratov-oblast":{"tags":["white","red","cyan","yellow"],"colors":[{"hex":"#ffffff","percent":60,"tag":"white"},{"hex":"#ff0000","percent":33,"tag":"red"},{"hex":"#1694dc","percent":2,"tag":"cyan"},{"hex":"#feeb6e","percent":1,"tag":"yellow"}]},"smolensk-oblast":{"tags":["red","yellow","gray"],"colors":[{"hex":"#ff0000","percent":84,"tag":"red"},{"hex":"#ffff00","percent":10,"tag":"yellow"},{"hex":"#c0c0c0","percent":3,"tag":"gray"},{"hex":"#ffd700","percent":1,"tag":"yellow"}]},"sverdlovsk-oblast":{"tags":["cyan","white","green"],"colors":[{"hex":"#187bbf","percent":45,"tag":"cyan"},{"hex":"#ffffff","percent":40,"tag":"white"},{"hex":"#15913d","percent":15,"tag":"green"}]},"tambov-oblast":{"tags":["red","cyan","yellow","white"],"colors":[{"hex":"#da251d","percent":44,"tag":"red"},{"hex":"#398fca","percent":40,"tag":"cyan"},{"hex":"#0093dd","percent":7,"tag":"cyan"},{"hex":"#fff500","percent":1,"tag":"yellow"},{"hex":"#f8c300","percent":1,"tag":"yellow"},{"hex":"#ffffff","percent":1,"tag":"white"}]},"tomsk-oblast":{"tags":["white","green","gray","yellow","red"],"colors":[{"hex":"#ffffff","percent":72,"tag":"white"},{"hex":"#00980a","percent":8,"tag":"green"},{"hex":"#333333","percent":3,"tag":"gray"},{"hex":"#ffb10d","percent":2,"tag":"yellow"},{"hex":"#fb240a","percent":1,"tag":"red"}]},"tula-oblast":{"tags":["red","white"],"colors":[{"hex":"#ff0000","percent":90,"tag":"red"},{"hex":"#ffffff","percent":3,"tag":"white"}]},"tver-oblast":{"tags":["yellow","red","black"],"colors":[{"hex":"#ffd700","percent":59,"tag":"yellow"},{"hex":"#d20000","percent":34,"tag":"red"},{"hex":"#000000","percent":4,"tag":"black"}]},"tyumen-oblast":{"tags":["white","green","blue","red","yellow"],"colors":[{"hex":"#ffffff","percent":30,"tag":"white"},{"hex":"#00923f","percent":30,"tag":"green"},{"hex":"#0051ba","percent":24,"tag":"blue"},{"hex":"#d81e05","percent":12,"tag":"red"},{"hex":"#ffd700","percent":2,"tag":"yellow"}]},"ulyanovsk-oblast":{"tags":["cyan","white"],"colors":[{"hex":"#009bde","percent":89,"tag":"cyan"},{"hex":"#ffffff","percent":6,"tag":"white"}]},"vladimir-oblast":{"tags":["red","cyan","yellow","black"],"colors":[{"hex":"#d52b1e","percent":77,"tag":"red"},{"hex":"#2aa6fe","percent":12,"tag":"cyan"},{"hex":"#fff500","percent":7,"tag":"yellow"},{"hex":"#000000","percent":1,"tag":"black"}]},"volgograd-oblast":{"tags":["red","blue","white"],"colors":[{"hex":"#fe0000","percent":80,"tag":"red"},{"hex":"#000184","percent":11,"tag":"blue"},{"hex":"#ffffff","percent":5,"tag":"white"},{"hex":"#ececec","percent":2,"tag":"white"},{"hex":"#32016a","percent":1,"tag":"blue"},{"hex":"#980035","percent":1,"tag":"red"}]},"vologda-oblast":{"tags":["white","red","gray","yellow"],"colors":[{"hex":"#ffffff","percent":72,"tag":"white"},{"hex":"#ff0000","percent":25,"tag":"red"},{"hex":"#c0c0c0","percent":1,"tag":"gray"},{"hex":"#ffd700","percent":1,"tag":"yellow"}]},"voronezh-oblast":{"tags":["red","yellow","white","black"],"colors":[{"hex":"#da251d","percent":68,"tag":"red"},{"hex":"#ffd400","percent":16,"tag":"yellow"},{"hex":"#ffffff","percent":8,"tag":"white"},{"hex":"#000000","percent":3,"tag":"black"},{"hex":"#f19e29","percent":2,"tag":"yellow"},{"hex":"#cccccc","percent":1,"tag":"white"}]},"yaroslavl-oblast":{"tags":["yellow","gray"],"colors":[{"hex":"#f8c301","percent":90,"tag":"yellow"},{"hex":"#2c2c2b","percent":7,"tag":"gray"}]},"moscow":{"tags":["red","black","white"],"colors":[{"hex":"#a8002c","percent":77,"tag":"red"},{"hex":"#161413","percent":7,"tag":"black"},{"hex":"#fffefc","percent":5,"tag":"white"}]},"saint-petersburg":{"tags":["red","white","yellow"],"colors":[{"hex":"#dc1b00","percent":93,"tag":"red"},{"hex":"#ffffff","percent":3,"tag":"white"},{"hex":"#e7a425","percent":1,"tag":"yellow"}]},"sevastopol":{"tags":["red","white","cyan","yellow"],"colors":[{"hex":"#d40000","percent":83,"tag":"red"},{"hex":"#ffffff","percent":6,"tag":"white"},{"hex":"#007ccc","percent":6,"tag":"cyan"},{"hex":"#ffd500","percent":1,"tag":"yellow"}]},"jewish-autonomous-oblast":{"tags":["white","red","yellow","green","blue","magenta"],"colors":[{"hex":"#ffffff","percent":83,"tag":"white"},{"hex":"#ff0000","percent":3,"tag":"red"},{"hex":"#ff9900","percent":3,"tag":"yellow"},{"hex":"#ffcc00","percent":3,"tag":"yellow"},{"hex":"#66cc33","percent":3,"tag":"green"},{"hex":"#3399ff","percent":3,"tag":"blue"},{"hex":"#0000cc","percent":3,"tag":"blue"},{"hex":"#660099","percent":3,"tag":"magenta"}]},"chukotka-autonomous-okrug":{"tags":["blue","white","yellow","red"],"colors":[{"hex":"#0039a6","percent":72,"tag":"blue"},{"hex":"#ffffff","percent":20,"tag":"white"},{"hex":"#ffd700","percent":6,"tag":"yellow"},{"hex":"#d52b1e","percent":1,"tag":"red"}]},"khanty-mansi-autonomous-okrug":{"tags":["green","blue","white"],"colors":[{"hex":"#00971c","percent":48,"tag":"green"},{"hex":"#2e96ff","percent":44,"tag":"blue"},{"hex":"#ffffff","percent":8,"tag":"white"}]},"nenets-autonomous-okrug":{"tags":["white","blue","green"],"colors":[{"hex":"#ffffff","percent":63,"tag":"white"},{"hex":"#0038a8","percent":25,"tag":"blue"},{"hex":"#008000","percent":12,"tag":"green"}]},"yamalo-nenets-autonomous-okrug":{"tags":["blue","white","red"],"colors":[{"hex":"#0080ff","percent":88,"tag":"blue"},{"hex":"#ffffff","percent":7,"tag":"white"},{"hex":"#ff0000","percent":2,"tag":"red"}]}}